en_blackbird_osint_ner/__init__.py
en_blackbird_osint_ner/meta.json
en_blackbird_osint_ner/en_blackbird_osint_ner-1.0.0/README.md
en_blackbird_osint_ner/en_blackbird_osint_ner-1.0.0/config.cfg
en_blackbird_osint_ner/en_blackbird_osint_ner-1.0.0/meta.json
en_blackbird_osint_ner/en_blackbird_osint_ner-1.0.0/tokenizer
en_blackbird_osint_ner/en_blackbird_osint_ner-1.0.0/attribute_ruler/patterns
en_blackbird_osint_ner/en_blackbird_osint_ner-1.0.0/lemmatizer/lookups/lookups.bin
en_blackbird_osint_ner/en_blackbird_osint_ner-1.0.0/ner/cfg
en_blackbird_osint_ner/en_blackbird_osint_ner-1.0.0/ner/model
en_blackbird_osint_ner/en_blackbird_osint_ner-1.0.0/ner/moves
en_blackbird_osint_ner/en_blackbird_osint_ner-1.0.0/parser/cfg
en_blackbird_osint_ner/en_blackbird_osint_ner-1.0.0/parser/model
en_blackbird_osint_ner/en_blackbird_osint_ner-1.0.0/parser/moves
en_blackbird_osint_ner/en_blackbird_osint_ner-1.0.0/senter/cfg
en_blackbird_osint_ner/en_blackbird_osint_ner-1.0.0/senter/model
en_blackbird_osint_ner/en_blackbird_osint_ner-1.0.0/tagger/cfg
en_blackbird_osint_ner/en_blackbird_osint_ner-1.0.0/tagger/model
en_blackbird_osint_ner/en_blackbird_osint_ner-1.0.0/tok2vec/cfg
en_blackbird_osint_ner/en_blackbird_osint_ner-1.0.0/tok2vec/model
en_blackbird_osint_ner/en_blackbird_osint_ner-1.0.0/vocab/key2row
en_blackbird_osint_ner/en_blackbird_osint_ner-1.0.0/vocab/lookups.bin
en_blackbird_osint_ner/en_blackbird_osint_ner-1.0.0/vocab/strings.json
en_blackbird_osint_ner/en_blackbird_osint_ner-1.0.0/vocab/vectors
en_blackbird_osint_ner/en_blackbird_osint_ner-1.0.0/vocab/vectors.cfg
en_blackbird_osint_ner-1.0.0.dist-info/METADATA
en_blackbird_osint_ner-1.0.0.dist-info/WHEEL
en_blackbird_osint_ner-1.0.0.dist-info/entry_points.txt
en_blackbird_osint_ner-1.0.0.dist-info/top_level.txt
en_blackbird_osint_ner-1.0.0.dist-info/RECORD
