Metadata-Version: 2.1
Name: en_blackbird_osint_ner
Version: 1.0.0
Summary: A SpaCy model for OSINT tasks with NER labels like NAME and AVATAR.
Home-page: https://github.com/p1ngul1n0/blackbird
Author: p1ngul1n0
Author-email: p1ngul1n0@protonmail.com
License: MIT
Requires-Dist: spacy<3.9.0,>=3.8.0
